LICENSE
README.md
setup.py
cloudtropy/__init__.py
cloudtropy/entropy_functions.py
cloudtropy/pmfs.py
cloudtropy.egg-info/PKG-INFO
cloudtropy.egg-info/SOURCES.txt
cloudtropy.egg-info/dependency_links.txt
cloudtropy.egg-info/requires.txt
cloudtropy.egg-info/top_level.txt