Metadata-Version: 1.1
Name: cloudtropy
Version: 0.0.2
Summary: Empirical probability mass functions and entropies of N-dimensional clouds of points.
Home-page: https://github.com/pedroramaciotti/Cloudtropy
Author: Pedro Ramaciotti Morales
Author-email: pedro.ramaciotti@gmail.com
License: UNKNOWN
Download-URL: https://github.com/pedroramaciotti/Cloudtropy/archive/0.0.1.tar.gz
Keywords: entropy,probabilities,entropy of points
Platform: UNKNOWN
